pdi/Signalling/Signal.py
pdi/Signalling/Event/AbstractEvent.py
pdi/Signalling/Event/Application.py
pdi/Signalling/Event/ClientExecuteError.py
pdi/Signalling/Event/DispatcherSpeak.py
pdi/Signalling/Event/Execute.py
pdi/Signalling/Event/Input.py
pdi/Signalling/Event/Logger.py
pdi/Signalling/Event/Print.py
pdi/Signalling/Event/Received.py
pdi/Signalling/Event/Server.py
pdi/Signalling/Event/Speak.py
raya_pdi-0.1.8.dist-info/METADATA
raya_pdi-0.1.8.dist-info/WHEEL
raya_pdi-0.1.8.dist-info/top_level.txt
raya_pdi-0.1.8.dist-info/RECORD
